dash_uploader_uppy5/__init__.py
dash_uploader_uppy5/configurator.py
dash_uploader_uppy5/settings.py
dash_uploader_uppy5/upload.py
dash_uploader_uppy5/uploadhandler.py
dash_uploader_uppy5/build/DashUploaderUppy5.py
dash_uploader_uppy5/build/__init__.py
dash_uploader_uppy5/build/_imports_.py
dash_uploader_uppy5/build/dash_uploader_uppy5.js
dash_uploader_uppy5/build/metadata.json
dash_uploader_uppy5/build/package-info.json
dash_uploader_uppy5/build/proptypes.js
dash_uploader_uppy5-0.2.0.dist-info/licenses/LICENSE
dash_uploader_uppy5-0.2.0.dist-info/METADATA
dash_uploader_uppy5-0.2.0.dist-info/WHEEL
dash_uploader_uppy5-0.2.0.dist-info/top_level.txt
dash_uploader_uppy5-0.2.0.dist-info/RECORD
