Metadata-Version: 2.4
Name: dash-uploader-uppy5
Version: 0.2.0
Summary: A modern Dash file uploader component powered by Uppy 5
Author-email: Zhixin Ou <ozx1072960726@gmail.com>
License-Expression: MIT
Project-URL: Homepages, https://github.com/Ozx-68102/dash-uploader-uppy5
Project-URL: Repository, https://github.com/Ozx-68102/dash-uploader-uppy5
Project-URL: Issues, https://github.com/Ozx-68102/dash-uploader-uppy5/issues
Keywords: dash,plotly,uppy,file-upload,react,flask,streaming
Classifier: Framework :: Dash
Classifier: Programming Language :: Python :: 3
Classifier: Programming Language :: Python :: 3.13
Classifier: Programming Language :: Python :: 3.14
Classifier: Operating System :: OS Independent
Requires-Python: >=3.13
License-File: LICENSE
Requires-Dist: dash>=3.3.0
Dynamic: license-file
